winney/__init__.py
winney/errors.py
winney/mock.py
winney/winney.py
winney-0.5.6.dist-info/LICENSE
winney-0.5.6.dist-info/METADATA
winney-0.5.6.dist-info/WHEEL
winney-0.5.6.dist-info/top_level.txt
winney-0.5.6.dist-info/RECORD
