Metadata-Version: 2.1
Name: winney
Version: 0.5.6
Summary: Object-Oriented HTTP Request
Home-page: https://github.com/olivetree123/winney
Author: olivetree
Author-email: olivetree123@163.com
License: MIT
Platform: UNKNOWN
Requires-Dist: requests (>=2.18.0)
